xontrib/broot.py
xontrib_broot-0.2.1.dist-info/LICENSE
xontrib_broot-0.2.1.dist-info/WHEEL
xontrib_broot-0.2.1.dist-info/METADATA
xontrib_broot-0.2.1.dist-info/RECORD
